{"name":"build-javascript","namedChunkGroups":{"app":{"name":"app","assets":[{"name":"webpack-runtime-b25183f1c3aa2e591846.js","size":3909},{"name":"framework-6dd5b9c1f46060dbc95a.js","size":141214},{"name":"styles.dbe93bf6f647b95e73e1.css","size":1256},{"name":"app-5c4a6c1442d1dd98a68b.js","size":96862}],"filteredAssets":0,"assetsSize":243241,"filteredAuxiliaryAssets":11,"auxiliaryAssetsSize":952235},"component---src-pages-404-tsx":{"name":"component---src-pages-404-tsx","assets":[{"name":"framework-6dd5b9c1f46060dbc95a.js","size":141214},{"name":"styles.dbe93bf6f647b95e73e1.css","size":1256},{"name":"commons-0be7e30c2b5d75656e4e.js","size":116662},{"name":"component---src-pages-404-tsx-298dd219e48ef810dac1.js","size":2766}],"filteredAssets":0,"assetsSize":261898,"filteredAuxiliaryAssets":11,"auxiliaryAssetsSize":1164039},"component---src-pages-index-tsx":{"name":"component---src-pages-index-tsx","assets":[{"name":"framework-6dd5b9c1f46060dbc95a.js","size":141214},{"name":"styles.dbe93bf6f647b95e73e1.css","size":1256},{"name":"b2e984c5-edcd58bb21e7db47dd2e.js","size":1103},{"name":"commons-0be7e30c2b5d75656e4e.js","size":116662},{"name":"component---src-pages-index-tsx-11ca4b6d82c36d8baa0a.js","size":57629}],"filteredAssets":0,"assetsSize":317864,"filteredAuxiliaryAssets":12,"auxiliaryAssetsSize":4255720},"component---src-pages-terms-of-service-tsx":{"name":"component---src-pages-terms-of-service-tsx","assets":[{"name":"framework-6dd5b9c1f46060dbc95a.js","size":141214},{"name":"styles.dbe93bf6f647b95e73e1.css","size":1256},{"name":"commons-0be7e30c2b5d75656e4e.js","size":116662},{"name":"component---src-pages-terms-of-service-tsx-2f729c2e6953976d02ca.js","size":3228}],"filteredAssets":0,"assetsSize":262360,"filteredAuxiliaryAssets":11,"auxiliaryAssetsSize":1165192}},"assetsByChunkName":{"app":["webpack-runtime-b25183f1c3aa2e591846.js","framework-6dd5b9c1f46060dbc95a.js","styles.dbe93bf6f647b95e73e1.css","app-5c4a6c1442d1dd98a68b.js"],"component---src-pages-404-tsx":["framework-6dd5b9c1f46060dbc95a.js","styles.dbe93bf6f647b95e73e1.css","commons-0be7e30c2b5d75656e4e.js","component---src-pages-404-tsx-298dd219e48ef810dac1.js"],"component---src-pages-index-tsx":["framework-6dd5b9c1f46060dbc95a.js","styles.dbe93bf6f647b95e73e1.css","b2e984c5-edcd58bb21e7db47dd2e.js","commons-0be7e30c2b5d75656e4e.js","component---src-pages-index-tsx-11ca4b6d82c36d8baa0a.js"],"component---src-pages-terms-of-service-tsx":["framework-6dd5b9c1f46060dbc95a.js","styles.dbe93bf6f647b95e73e1.css","commons-0be7e30c2b5d75656e4e.js","component---src-pages-terms-of-service-tsx-2f729c2e6953976d02ca.js"]},"childAssetsByChunkName":{}}